icatcher/__init__.py
icatcher/cli.py
icatcher/draw.py
icatcher/face_detector.py
icatcher/models.py
icatcher/options.py
icatcher/parsers.py
icatcher/ui_packaging.py
icatcher/video.py
icatcher/icatcher_app/api/__init__.py
icatcher/icatcher_app/api/api.py
icatcher/icatcher_app/api/builder.py
icatcher/icatcher_app/frontend/build/asset-manifest.json
icatcher/icatcher_app/frontend/build/favicon.ico
icatcher/icatcher_app/frontend/build/index.html
icatcher/icatcher_app/frontend/build/logo192.png
icatcher/icatcher_app/frontend/build/logo512.png
icatcher/icatcher_app/frontend/build/manifest.json
icatcher/icatcher_app/frontend/build/robots.txt
icatcher/icatcher_app/frontend/build/static/css/main.da4efd19.css
icatcher/icatcher_app/frontend/build/static/css/main.da4efd19.css.map
icatcher/icatcher_app/frontend/build/static/js/787.63654d8f.chunk.js
icatcher/icatcher_app/frontend/build/static/js/787.63654d8f.chunk.js.map
icatcher/icatcher_app/frontend/build/static/js/main.0a3ffe26.js
icatcher/icatcher_app/frontend/build/static/js/main.0a3ffe26.js.LICENSE.txt
icatcher/icatcher_app/frontend/build/static/js/main.0a3ffe26.js.map
icatcher/icatcher_app/frontend/node_modules/flatted/python/flatted.py
icatcher/icatcher_app/frontend/node_modules/flatted/python/test.py
icatcher-0.2.3.dist-info/LICENSE
icatcher-0.2.3.dist-info/METADATA
icatcher-0.2.3.dist-info/WHEEL
icatcher-0.2.3.dist-info/entry_points.txt
icatcher-0.2.3.dist-info/top_level.txt
icatcher-0.2.3.dist-info/RECORD
