Metadata-Version: 2.1
Name: icatcher
Version: 0.2.3
Summary: iCatcher+: Robust and automated annotation of infant gaze from videos collected in laboratory, field, and online studies.
Author-email: Yotam Erel <erelyotam@gmail.com>
License: GNU GENERAL PUBLIC LICENSE
Project-URL: Homepage, https://github.com/yoterel/icatcher_plus
Keywords: eyetracker,eyetracking
Classifier: Programming Language :: Python
Classifier: Programming Language :: Python :: 3
Requires-Python: >=3.9
License-File: LICENSE
Requires-Dist: torch >=1.11.0
Requires-Dist: torchvision >=0.12
Requires-Dist: numpy
Requires-Dist: Pillow
Requires-Dist: ffmpeg-python
Requires-Dist: opencv-python
Requires-Dist: tqdm
Requires-Dist: pooch
Requires-Dist: batch-face
Requires-Dist: pathos
Requires-Dist: flask
Requires-Dist: flask-cors
Provides-Extra: build
Requires-Dist: bumpver ; extra == 'build'
Requires-Dist: build ; extra == 'build'
Requires-Dist: twine ; extra == 'build'
Provides-Extra: dev
Requires-Dist: pytest ; extra == 'dev'
